aranya_calc/__init__.py
aranya_calc/calc.py
aranya_calc-1.0.0.dist-info/METADATA
aranya_calc-1.0.0.dist-info/WHEEL
aranya_calc-1.0.0.dist-info/licenses/LICENCE.txt
aranya_calc-1.0.0.dist-info/RECORD
