Metadata-Version: 2.1
Name: aranya_calc
Version: 1.0.0
Summary: A simple calculator package
Author-email: Aranya Pal <palaranya04@gmail.com>
License-File: LICENCE.txt
Classifier: License :: OSI Approved :: MIT License
Classifier: Operating System :: OS Independent
Classifier: Programming Language :: Python :: 3
Requires-Python: >=3.7
